odoo8_addon_contract_recurring_invoicing_monthly_last_day-8.0.1.0.0-py2.7-nspkg.pth
odoo_addons/contract_recurring_invoicing_monthly_last_day/__openerp__.py
odoo_addons/contract_recurring_invoicing_monthly_last_day/__init__.py
odoo_addons/contract_recurring_invoicing_monthly_last_day/README.rst
odoo_addons/contract_recurring_invoicing_monthly_last_day/models/__init__.py
odoo_addons/contract_recurring_invoicing_monthly_last_day/models/contract.py
odoo_addons/contract_recurring_invoicing_monthly_last_day/i18n/es.po
odoo_addons/contract_recurring_invoicing_monthly_last_day/test/contract_recurring_invoicing_monthly_last_day.yml
odoo8_addon_contract_recurring_invoicing_monthly_last_day-8.0.1.0.0.dist-info/top_level.txt
odoo8_addon_contract_recurring_invoicing_monthly_last_day-8.0.1.0.0.dist-info/WHEEL
odoo8_addon_contract_recurring_invoicing_monthly_last_day-8.0.1.0.0.dist-info/RECORD
odoo8_addon_contract_recurring_invoicing_monthly_last_day-8.0.1.0.0.dist-info/metadata.json
odoo8_addon_contract_recurring_invoicing_monthly_last_day-8.0.1.0.0.dist-info/DESCRIPTION.rst
odoo8_addon_contract_recurring_invoicing_monthly_last_day-8.0.1.0.0.dist-info/METADATA
odoo8_addon_contract_recurring_invoicing_monthly_last_day-8.0.1.0.0.dist-info/namespace_packages.txt
